pronounce/__init__.py
pronounce-1.0.0.dist-info/LICENSE.txt
pronounce-1.0.0.dist-info/METADATA
pronounce-1.0.0.dist-info/WHEEL
pronounce-1.0.0.dist-info/top_level.txt
pronounce-1.0.0.dist-info/RECORD
