Metadata-Version: 2.1
Name: pronounce
Version: 1.0.0
Summary: Generate the pronunciation code for the string
Home-page: https://github.com/vish0709/pronounce/
Author: Vishal Kumar
Author-email: vtkumar022@gmail.com
License: UNKNOWN
Platform: UNKNOWN
Classifier: Programming Language :: Python :: 3
Classifier: License :: OSI Approved :: MIT License
Classifier: Operating System :: OS Independent
